wp_api/__init__.py
wp_api/auth.py
wp_api/client.py
wp_api/exceptions.py
wp_api/endpoints/__init__.py
wp_api/endpoints/base.py
wp_api/endpoints/block_patterns.py
wp_api/endpoints/categories.py
wp_api/endpoints/comments.py
wp_api/endpoints/custom_fields.py
wp_api/endpoints/custom_post_types.py
wp_api/endpoints/media.py
wp_api/endpoints/pages.py
wp_api/endpoints/posts.py
wp_api/endpoints/settings.py
wp_api/endpoints/tags.py
wp_api/endpoints/taxonomies.py
wp_api/endpoints/users.py
wp_api_client-0.1.0.dist-info/licenses/LICENSE
wp_api_client-0.1.0.dist-info/METADATA
wp_api_client-0.1.0.dist-info/WHEEL
wp_api_client-0.1.0.dist-info/top_level.txt
wp_api_client-0.1.0.dist-info/RECORD
