Metadata-Version: 2.4
Name: wp-api-client
Version: 0.1.0
Summary: Python client for the WordPress REST API
Home-page: https://github.com/innerkorehq/wp-api-client
Author: Gagan (innerkore)
Author-email: gagan@innerkore.com
Project-URL: Bug Reports, https://github.com/innerkorehq/wp-api-client/issues
Project-URL: Source, https://github.com/innerkorehq/wp-api-client
Project-URL: Documentation, https://wp-api-client.readthedocs.io/
Keywords: wordpress,api,rest,wp-api
Classifier: Development Status :: 3 - Alpha
Classifier: Intended Audience :: Developers
Classifier: License :: OSI Approved :: MIT License
Classifier: Programming Language :: Python :: 3
Classifier: Programming Language :: Python :: 3.6
Classifier: Programming Language :: Python :: 3.7
Classifier: Programming Language :: Python :: 3.8
Classifier: Programming Language :: Python :: 3.9
Classifier: Programming Language :: Python :: 3.10
Classifier: Programming Language :: Python :: 3.11
Classifier: Programming Language :: Python :: 3.12
Classifier: Programming Language :: Python :: 3.13
Classifier: Topic :: Software Development :: Libraries :: Python Modules
Requires-Python: >=3.6
License-File: LICENSE
Requires-Dist: requests>=2.25.0
Provides-Extra: dev
Requires-Dist: pytest>=6.0.0; extra == "dev"
Requires-Dist: pytest-cov>=2.10.0; extra == "dev"
Requires-Dist: black>=20.8b1; extra == "dev"
Requires-Dist: flake8>=3.8.0; extra == "dev"
Requires-Dist: mypy>=0.800; extra == "dev"
Requires-Dist: isort>=5.0.0; extra == "dev"
Requires-Dist: tox>=3.20.0; extra == "dev"
Requires-Dist: sphinx>=3.0.0; extra == "dev"
Requires-Dist: sphinx-rtd-theme>=0.5.0; extra == "dev"
Requires-Dist: sphinx-autodoc-typehints>=1.12.0; extra == "dev"
Requires-Dist: twine>=3.3.0; extra == "dev"
Requires-Dist: build>=0.5.0; extra == "dev"
Requires-Dist: wheel>=0.36.2; extra == "dev"
Provides-Extra: docs
Requires-Dist: sphinx>=3.0.0; extra == "docs"
Requires-Dist: sphinx-rtd-theme>=0.5.0; extra == "docs"
Requires-Dist: sphinx-autodoc-typehints>=1.12.0; extra == "docs"
Dynamic: author
Dynamic: author-email
Dynamic: classifier
Dynamic: description
Dynamic: description-content-type
Dynamic: home-page
Dynamic: keywords
Dynamic: license-file
Dynamic: project-url
Dynamic: provides-extra
Dynamic: requires-dist
Dynamic: requires-python
Dynamic: summary
